NightWindAudioLib/__init__.py
NightWindAudioLib/audio.py
NightWindAudioLib/channel.py
NightWindAudioLib/left_and_right.py
NightWindAudioLib/listening.py
NightWindAudioLib/media_tool.py
NightWindAudioLib/produce.py
NightWindAudioLib/remix.py
NightWindAudioLib/__pycache__/__init__.cpython-38.pyc
NightWindAudioLib/__pycache__/audio.cpython-38.pyc
NightWindAudioLib/__pycache__/listening.cpython-38.pyc
NightWindAudioLib/__pycache__/media_tool.cpython-38.pyc
NightWindAudioLib/__pycache__/produce.cpython-38.pyc
NightWindAudioLib/__pycache__/remix.cpython-38.pyc
NightWindAudioLib/channel/模式之歌.mp3
NightWindAudioLib/channel/编程猫的梦想.mp3
NightWindAudioLib/produce/Do.wav
NightWindAudioLib/produce/Do2.wav
NightWindAudioLib/produce/Fa.wav
NightWindAudioLib/produce/La.wav
NightWindAudioLib/produce/Mi.wav
NightWindAudioLib/produce/Re.wav
NightWindAudioLib/produce/Si.wav
NightWindAudioLib/produce/Sol.wav
NightWindAudioLib/produce/demo.wav
NightWindAudioLib/produce/人声.mp3
NightWindAudioLib/pydub_audio/music.mp3
NightWindAudioLib/pydub_audio/music.wav
NightWindAudioLib/pydub_audio/music_result.mp3
NightWindAudioLib/pydub_audio/random_sounds.mp3
NightWindAudioLib/pydub_audio/他是编程猫.mp3
NightWindAudioLib/pydub_audio/可爱起床歌.mp3
NightWindAudioLib/pydub_audio/听写单词.mp3
NightWindAudioLib/pydub_audio/我是阿短.mp3
NightWindAudioLib/pydub_audio/海棠不言 - 编程猫的梦想.mp3
NightWindAudioLib/pydub_audio/瓜瓜为何不发芽.mp3
NightWindAudioLib/pydub_audio/跟我学唱循环歌.mp3
NightWindAudioLib/remix/四句儿歌小可.mp3
NightWindAudioLib/remix/四句儿歌编程猫.mp3
NightWindAudioLib/remix/旋律.mp3
NightWindAudioLib/remix/鼓点.mp3
NightWindAudioLib/song/song.py
NightWindAudioLib/song/可爱起床歌.mp3
NightWindAudioLib/song/瓜瓜为何不发芽.mp3
NightWindAudioLib/song/跟我学唱循环歌.mp3
NightWindAudioLib/song/__pycache__/song.cpython-38.pyc
NightWindAudioLib-0.0.1.dist-info/METADATA
NightWindAudioLib-0.0.1.dist-info/WHEEL
NightWindAudioLib-0.0.1.dist-info/top_level.txt
NightWindAudioLib-0.0.1.dist-info/RECORD
