Metadata-Version: 2.1
Name: NightWindAudioLib
Version: 0.0.1
Summary: Some little games of audio
Home-page: https://github.com/
Author: Nova_NightWind0311
Author-email: 
License: UNKNOWN
Platform: UNKNOWN
Classifier: Programming Language :: Python :: 3
Classifier: License :: OSI Approved :: MIT License
Classifier: Operating System :: OS Independent
Requires-Dist: pydub (>=0.24)
Requires-Dist: simpleaudio (>=1.0)
